setup.py
cs_probdist/Binomialdistribution.py
cs_probdist/Gaussiandistribution.py
cs_probdist/Generaldistribution.py
cs_probdist/__init__.py
cs_probdist.egg-info/PKG-INFO
cs_probdist.egg-info/SOURCES.txt
cs_probdist.egg-info/dependency_links.txt
cs_probdist.egg-info/not-zip-safe
cs_probdist.egg-info/top_level.txt