Metadata-Version: 1.0
Name: cs-probdist
Version: 1.0
Summary: Gaussian and Binomial cs_probdist
Home-page: UNKNOWN
Author: Chezka Sino
Author-email: chezka@pm.me
License: UNKNOWN
Platform: UNKNOWN
